README.md
setup.py
src/maxim/__init__.py
src/maxim/maxim.py
src/maxim/sub_maxim.py
src/maxim.egg-info/PKG-INFO
src/maxim.egg-info/SOURCES.txt
src/maxim.egg-info/dependency_links.txt
src/maxim.egg-info/entry_points.txt
src/maxim.egg-info/requires.txt
src/maxim.egg-info/top_level.txt